toffy/__init__.py
toffy/bin_extraction.py
toffy/detector_sweep.py
toffy/file_hash.py
toffy/fov_watcher.py
toffy/image_stitching.py
toffy/json_utils.py
toffy/mibitracker_utils.py
toffy/mph_comp.py
toffy/mph_inspect.py
toffy/normalize.py
toffy/panel_utils.py
toffy/qc_comp.py
toffy/qc_metrics_plots.py
toffy/reorg.py
toffy/rosetta.py
toffy/settings.py
toffy/streak_detection.py
toffy/tiling_utils.py
toffy/watcher_callbacks.py
toffy-0.3.3.dist-info/LICENSE
toffy-0.3.3.dist-info/METADATA
toffy-0.3.3.dist-info/WHEEL
toffy-0.3.3.dist-info/RECORD
