Metadata-Version: 2.1
Name: Toffy
Version: 0.3.3
Summary: Scripts for interacting with and generating data from the commercial MIBIScope.
Home-page: https://github.com/angelolab/toffy
License: Modified Apache 2.0
Author: Noah Frey Greenwald
Author-email: nfgreen@stanford.edu
Requires-Python: >=3.9,<3.12
Classifier: Development Status :: 4 - Beta
Classifier: License :: OSI Approved :: Apache Software License
Classifier: License :: Other/Proprietary License
Classifier: Programming Language :: Python :: 3
Classifier: Programming Language :: Python :: 3.9
Classifier: Programming Language :: Python :: 3.10
Classifier: Programming Language :: Python :: 3.11
Requires-Dist: alpineer (>=0.1.10)
Requires-Dist: ipywidgets (>=8,<9)
Requires-Dist: mibi-bin-tools (>=0.2.14)
Requires-Dist: natsort (>=8,<9)
Requires-Dist: numpy (==1.*)
Requires-Dist: pandas (>=2,<3)
Requires-Dist: pywavelets (>=1.4.1,<2.0.0)
Requires-Dist: scikit-learn (>=1,<2)
Requires-Dist: scipy (>=1.10.1,<2.0.0)
Requires-Dist: seaborn (>=0.13,<0.14)
Requires-Dist: tqdm (>=4,<5)
Requires-Dist: watchdog (>=6,<7)
Project-URL: Documentation, https://toffy.readthedocs.io
Project-URL: Repository, https://github.com/angelolab/toffy
